netbox_exporter/__init__.py
netbox_exporter/cli.py
netbox_exporter/exporter.py
netbox_exporter/fetcher.py
netbox_exporter-0.1.2.dist-info/LICENSE
netbox_exporter-0.1.2.dist-info/METADATA
netbox_exporter-0.1.2.dist-info/WHEEL
netbox_exporter-0.1.2.dist-info/entry_points.txt
netbox_exporter-0.1.2.dist-info/top_level.txt
netbox_exporter-0.1.2.dist-info/RECORD
