Metadata-Version: 2.1
Name: netbox-exporter
Version: 0.1.2
Summary: 'Fetch and export your Netbox inventory to a local directory.'
Home-page: https://github.com/baccenfutter/netbox_exporter
Author: Brian Wiborg
Author-email: wiborg@team.snafu.de
License: UNKNOWN
Project-URL: Bug Tracker, https://github.com/baccenfutter/netbox_exporter/issues
Platform: UNKNOWN
Classifier: Programming Language :: Python :: 3
Classifier: License :: OSI Approved :: GNU General Public License v2 (GPLv2)
Classifier: Operating System :: OS Independent
Requires-Python: >=3.6
License-File: LICENSE
Requires-Dist: click
Requires-Dist: netbox-client
Requires-Dist: requests
Requires-Dist: pyyaml
Provides-Extra: dev
Requires-Dist: build ; extra == 'dev'
Requires-Dist: ipython ; extra == 'dev'
Requires-Dist: prompt-toolkit ; extra == 'dev'
Requires-Dist: pylint ; extra == 'dev'
Requires-Dist: twine ; extra == 'dev'
